setup.py
rj_distributions/Binomialdistribution.py
rj_distributions/Gaussiandistribution.py
rj_distributions/Generaldistribution.py
rj_distributions/__init__.py
rj_distributions.egg-info/PKG-INFO
rj_distributions.egg-info/SOURCES.txt
rj_distributions.egg-info/dependency_links.txt
rj_distributions.egg-info/not-zip-safe
rj_distributions.egg-info/top_level.txt