Metadata-Version: 1.0
Name: rj-distributions
Version: 0.0.1
Summary: Gaussian distributions
Home-page: UNKNOWN
Author: Rijul Paul
Author-email: rijul90@gmail.com
License: UNKNOWN
Platform: UNKNOWN
